<?xml version='1.0' encoding='UTF-8'?>
<szpital>
    <oddzialy>
        <oddzial>Chirurgiczny</oddzial>
        <oddzial>Onkologiczny</oddzial>
        <oddzial>Położniczy</oddzial>
        <oddzial>Kardiologiczny</oddzial>
        <oddzial>Internistyczny</oddzial>
    </oddzialy>
    <karetki>
        <karetka nr_rej='NBR12345'>
            <marka>Mercedes</marka>
            <model>Sprinter</model>
        </karetka>
        <karetka nr_rej='NBR54321'>
            <marka>Volkswagen</marka>
            <model>Transporter</model>
        </karetka>
        <karetka nr_rej='NBR54123'>
            <marka>Volkswagen</marka>
            <model>Transporter</model>
        </karetka>
    </karetki>
    <środki_ochrony>
         <środek_ochrony>
            <nazwa>Rękawiczki lateksowe</nazwa>
            <ilość>5000</ilość>
        </środek_ochrony>
        <środek_ochrony>
            <nazwa>Maseczki chirurgiczne</nazwa>
            <ilość>400</ilość>
        </środek_ochrony>
        <środek_ochrony>
            <nazwa>Fartuch ochronny</nazwa>
            <ilość>500</ilość>
        </środek_ochrony>
    </środki_ochrony>
    <pracownicy>
        <lekarze>
            <lekarz plec='m' id='L1' oddzial='Onkologiczny'>
                <imie>Grzegorz</imie>
                <nazwisko>Brzeczyszczykiewicz</nazwisko>
                <data_ur>1983-03-12</data_ur>
                <specjalizacja>Onkologia</specjalizacja>
                <pensja>6700</pensja>
            </lekarz>
            <lekarz plec='m' id='L2' oddzial='Kardiologiczny'>
                <imie>Bartłomiej</imie>
                <nazwisko>Żak</nazwisko>
                <data_ur>1970-02-21</data_ur>
                <specjalizacja>Kardiologia</specjalizacja>
                <pensja>9000</pensja>
            </lekarz>
            <lekarz plec='m' id='L4' oddzial='Położniczy'>
                <imie>Kazimierz</imie>
                <nazwisko>Kotłowski</nazwisko>
                <data_ur>1986-12-17</data_ur>
                <specjalizacja>Ginekologia</specjalizacja>
                <pensja>6000</pensja>
            </lekarz>
            <lekarz plec='k' id='L5' oddzial='Chirurgiczny'>
                <imie>Alicja</imie>
                <nazwisko>Czarnogórska</nazwisko>
                <data_ur>1979-11-16</data_ur>
                <specjalizacja>Chirurgia</specjalizacja>
                <pensja>11000</pensja>
            </lekarz>
        </lekarze>
        <pielegniarki>
            <pielegniarka id='P1' oddzial='Położniczy'>
                <imie>Katarzyna</imie>
                <nazwisko>Anglosaska</nazwisko>
                <data_ur>1969-12-21</data_ur>
                <specjalizacja>Ginekologiczno-położnicza</specjalizacja>
                <pensja>3000</pensja>
            </pielegniarka>
            <pielegniarka id='P3' oddzial='Onkologiczny'>
                <imie>Grażyna</imie>
                <nazwisko>Mysiel</nazwisko>
                <data_ur>1994-02-13</data_ur>
                <specjalizacja>Onkologiczna</specjalizacja>
                <pensja>2700</pensja>
            </pielegniarka>
            <pielegniarka id='P4' oddzial='Kardiologiczny'>
                <imie>Anna</imie>
                <nazwisko>Skowronek</nazwisko>
                <data_ur>1995-03-12</data_ur>
                <specjalizacja>Kardiologiczna</specjalizacja>
                <pensja>2500</pensja>
            </pielegniarka>
            <pielegniarka id='P5' oddzial='Chirurgiczny'>
                <imie>Karolina</imie>
                <nazwisko>Borowska</nazwisko>
                <data_ur>1971-05-06</data_ur>
                <specjalizacja>Chirurgiczna</specjalizacja>
                <pensja>3200</pensja>
            </pielegniarka>
        </pielegniarki>
        <ratownicy_medyczni>
            <ratownik plec='m' id='R1'>
                <imie>Xawery</imie>
                <nazwisko>Kula</nazwisko>
                <data_ur>1996-06-21</data_ur>
                <pensja>3000</pensja>
            </ratownik>
            <ratownik plec='k' id='R2'>
                <imie>Matylda</imie>
                <nazwisko>Sobolewska</nazwisko>
                <data_ur>1979-01-23</data_ur>
                <pensja>3000</pensja>
            </ratownik>
            <ratownik plec='m' id='R3'>
                <imie>Roman</imie>
                <nazwisko>Pilot</nazwisko>
                <data_ur>1982-09-03</data_ur>
                <pensja>3000</pensja>
            </ratownik>
        </ratownicy_medyczni>
    </pracownicy>
    <pacjenci>
        <pacjent plec='m' id='PA1' oddzial='Onkologiczny'>
            <imie>Karol</imie>
            <nazwisko>Bosak</nazwisko>
            <pesel></pesel>
            <diagnoza>Rak płuc</diagnoza>
        </pacjent>
        <pacjent plec='m' id='PA2' oddzial='Chirurgiczny'>
            <imie>Bartłomiej</imie>
            <nazwisko>Katar</nazwisko>
            <pesel></pesel>
            <diagnoza>Rana kłuta</diagnoza>
        </pacjent>
        <pacjent plec='k' id='PA3' oddzial='Ginekologiczny'>
            <imie>Joanna</imie>
            <nazwisko>Kosakowska</nazwisko>
            <pesel></pesel>
            <diagnoza>Poród</diagnoza>
        </pacjent>
        <pacjent plec='m' id='PA4' oddzial='Kardiologiczny'>
            <imie>Seweryn</imie>
            <nazwisko>Andrzej</nazwisko>
            <pesel></pesel>
            <diagnoza>Arytmia serca</diagnoza>
        </pacjent>
    </pacjenci>
</szpital>